{
  "id": "hakkeijima",
  "name": "Hakkeijima Sea Paradise",
  "region": "Kanto",
  "categories": ["Theme Park", "Aquarium"],
  "tags": ["Family", "Entertainment"],
  "budgetRecommended": 21800,
  "ratings": {
    "overall": 8.4,
    "photography": 7.5,
    "food": 7,
    "summer": 8.5,
    "couple": 8,
    "winter": 7,
    "rain": 6,
    "relaxation": 8,
    "value": 8,
    "uniqueness": 8
  },
  "indoorPercent": 70,
  "coordinates": {
    "lat": 35.3375,
    "lng": 139.6453
  },
  "heroImage": "https://upload.wikimedia.org/wikipedia/commons/1/13/Yokohama_Hakkeijima_Sea_Paradise_2015_%28crop%29.jpg",
  "prefecture": "Kanagawa",
  "budgetMin": 17800,
  "budgetMax": 25800,
  "totalTripHours": 8,
  "walkingMin": 10000,
  "walkingSunMin": 4000,
  "walkingShadeMin": 6000,
  "comfort": {
    "heatTolerance": 9,
    "rainFriendly": 9,
    "walkingIntensity": 5
  },
  "transportOptions": {
    "train": 45,
    "car": 40
  },
  "crowd": {
    "weekday": 3,
    "weekend": 4,
    "holiday": 5
  },
  "season": {
    "spring": 4,
    "summer": 4,
    "autumn": 4,
    "winter": 4
  },
  "highlights": ["Hakkeijima Sea Paradise"],
  "description": "Hakkeijima Sea Paradise is a scenic destination in the Kanagawa region of Japan, offering rich history and cultural attractions.",
  "bestMonths": [3, 4, 5, 9, 10, 11]
}
