{
  "id": "shibuya-ward",
  "name": "Shibuya",
  "prefecture": "Tokyo",
  "region": "Kanto",
  "categories": ["City", "Shopping"],
  "heroImage": "https://upload.wikimedia.org/wikipedia/commons/thumb/8/88/Shibuya_Crossing%2C_Aerial.jpg/960px-Shibuya_Crossing%2C_Aerial.jpg",
  "gallery": [],
  "description": "Youth culture, trendy fashion, and the iconic Shibuya Scramble Crossing. Constantly evolving with new high-rises like Shibuya Sky.",
  "totalTripHours": 8,
  "budgetMin": 6000,
  "budgetRecommended": 9000,
  "budgetMax": 14000,
  "walkingMin": 10000,
  "walkingSunMin": 6000,
  "walkingShadeMin": 4000,
  "indoorPercent": 50,
  "ratings": {
    "overall": 9,
    "couple": 9,
    "summer": 7.5,
    "winter": 8.5,
    "rain": 7.5,
    "food": 9,
    "photography": 9.5,
    "relaxation": 6,
    "value": 8,
    "uniqueness": 9.5
  },
  "crowd": {
    "weekday": 9,
    "weekend": 10,
    "holiday": 10
  },
  "season": {
    "spring": 8,
    "summer": 7,
    "autumn": 8,
    "winter": 9
  },
  "bestMonths": [3, 4, 9, 10, 11, 12],
  "reservation": "Required for Shibuya Sky.",
  "parking": "Extremely difficult.",
  "highlights": ["Scramble Crossing", "Shibuya Sky", "Miyashita Park"],
  "tags": ["Trendy", "Photography", "Fashion"],
  "itinerary": [],
  "restaurants": ["Katsumidori Seibu Shibuya"],
  "cafes": ["Fuglen Tokyo"],
  "notes": "Book Shibuya Sky tickets for sunset at least 2 weeks in advance.",
  "itineraries": [
    {
      "name": "Classic Day Trip",
      "description": "The most efficient way to see the highlights of Shibuya in one day.",
      "steps": [
        {
          "time": "10:00 AM",
          "activity": "Arrive at the main station and get oriented."
        },
        {
          "time": "11:00 AM",
          "activity": "Visit the primary city attraction."
        },
        {
          "time": "1:00 PM",
          "activity": "Grab a delicious regional lunch."
        },
        {
          "time": "2:30 PM",
          "activity": "Continue exploring the scenic sights."
        },
        {
          "time": "4:30 PM",
          "activity": "Relax at a local café before heading back."
        }
      ]
    }
  ],
  "coordinates": {
    "lat": 35.6637109,
    "lng": 139.6976941
  },
  "budgetBreakdown": {
    "transport": 1000,
    "tickets": 0,
    "food": 6000,
    "cafe": 2000
  },
  "comfort": {
    "heatTolerance": 7.5,
    "rainFriendly": 5,
    "walkingIntensity": 10
  },
  "image": "https://loremflickr.com/1000/800/japan,shibuya/all?lock=1027",
  "transportOptions": {
    "train": 40
  }
}
